files_to_chat/__init__.py
files_to_chat/cli.py
files_to_chat/docs.py
files_to_chat/prompt_cache.py
files_to_chat-0.1.3.dist-info/METADATA
files_to_chat-0.1.3.dist-info/WHEEL
files_to_chat-0.1.3.dist-info/entry_points.txt
files_to_chat-0.1.3.dist-info/RECORD
