Metadata-Version: 2.4
Name: files-to-chat
Version: 0.1.3
Summary: `files-to-chat` is a command-line tool designed to process files or folders, converting their contents into a format suitable for use as a prompt context to chat with large language models (LLMs).
Author-email: anchen <li.anchen.au@gmail.com>
Requires-Python: >=3.11
Requires-Dist: docling>=2.18.0
Requires-Dist: mlx-lm>=0.21.1
Requires-Dist: mlx>=0.22.0
Requires-Dist: transformers>=4.42.4
